MANIFEST.in
README.rst
setup.cfg
setup.py
pylegos/__init__.py
pylegos/app_platform.py
pylegos/core.py
pylegos/pylegos_properties.py
pylegos/utils.py
pylegos.egg-info/PKG-INFO
pylegos.egg-info/SOURCES.txt
pylegos.egg-info/dependency_links.txt
pylegos.egg-info/entry_points.txt
pylegos.egg-info/requires.txt
pylegos.egg-info/top_level.txt
pylegos/cli/__init__.py
pylegos/cli/pycli-orig.py
pylegos/cli/pycli.py
pylegos/cli/pycli_controllers.py
pylegos/cli/pycli_services.py
pylegos/cli/templates/code/app.tpl
pylegos/cli/templates/code/app_controllers.tpl
pylegos/cli/templates/code/app_models.tpl
pylegos/cli/templates/code/app_services.tpl
pylegos/cli/templates/code/build.py
pylegos/cli/templates/code/database_initial_seed_data.tpl
pylegos/cli/templates/code/module.tpl
pylegos/cli/templates/code/module_controllers.tpl
pylegos/cli/templates/code/module_models.tpl
pylegos/cli/templates/code/module_services.tpl
pylegos/cli/templates/config/app.ini
pylegos/cli/templates/config/database-userInfo.tpl
pylegos/cli/templates/config/database-userPrivs.tpl
pylegos/cli/templates/config/modBaseManifest.tpl
pylegos/cli/templates/config/model-def.README
pylegos/cli/templates/config/modelDef.tpl
pylegos/cli/templates/config/module.ini
pylegos/cli/templates/config/package.template
pylegos/cli/templates/launchers/app.sh
pylegos/cli/templates/launchers/mod.sh
tests/test_projects/__init__.py
tests/test_projects/foo/__init__.py
tests/test_projects/foo/app/__init__.py
tests/test_projects/foo/app/modules/__init__.py
tests/test_projects/foo/app/modules/moda/__init__.py
tests/test_projects/foo/app/modules/moda/moda.py
tests/test_projects/foo/app/modules/moda/moda_controllers.py
tests/test_projects/foo/app/modules/moda/moda_services.py
tests/test_projects/foo/app/modules/moda/moda_settings_def.py
tests/test_projects/foo/app/modules/modb/__init__.py
tests/test_projects/foo/conf/__init__.py
tests/test_projects/foo/conf/moda_settings.py