Metadata-Version: 1.1
Name: pylegos
Version: 0.1.0a2
Summary: A python framework for enterprise projects
Home-page: https://github.com/velexio/pylegos
Author: Gerry Christiansen
Author-email: gchristiansen@velexio.com, gchristiansen@gmail.com
License: MIT
Keywords: framework enterprise development libraries database tools
Platform: UNKNOWN
Classifier: Development Status :: 2 - Pre-Alpha
Classifier: Intended Audience :: Developers
Classifier: Topic :: Software Development :: Libraries :: Application Frameworks
Classifier: License :: OSI Approved :: MIT License
Classifier: Programming Language :: Python :: 3
